deepeye_pack/__init__.py
deepeye_pack/features.py
deepeye_pack/instance.py
deepeye_pack/main.py
deepeye_pack/myGraph.py
deepeye_pack/table.py
deepeye_pack/table_l.py
deepeye_pack/view.py
deepeye_pack/jars/RankLib.jar
deepeye_pack/jars/rank.model
deepeye_pack-0.2.dist-info/METADATA
deepeye_pack-0.2.dist-info/RECORD
deepeye_pack-0.2.dist-info/WHEEL
deepeye_pack-0.2.dist-info/top_level.txt
