Metadata-Version: 2.1
Name: deepeye-pack
Version: 0.2
Summary: a Python package for DeepEye:Towards automatic Data Visualization API
Home-page: https://github.com/TsinghuaDatabaseGroup/DeepEye/tree/master/APIs_Deepeye
Author: tpchris1
Author-email: topchrischang@hotmail.com
License: MIT
Platform: UNKNOWN
Classifier: Development Status :: 3 - Alpha
Classifier: License :: OSI Approved :: MIT License
Classifier: Programming Language :: Python :: 2.7
Classifier: Topic :: Text Processing :: Linguistic
Requires-Dist: numpy
Requires-Dist: pandas
Requires-Dist: MySQLdb
Requires-Dist: pyecharts
Requires-Dist: pprint
